{
  "generated_at": "2026-07-22T15:20:23Z",
  "categories": [
    {
      "name": "Indices",
      "items": [
        {
          "symbol": "^GSPC",
          "label": "S&P 500",
          "price": 7514.37,
          "change_pct": 0.06884627594197129,
          "high": 7519.22,
          "low": 7485.85
        },
        {
          "symbol": "^DJI",
          "label": "Dow Jones",
          "price": 52309.58,
          "change_pct": 0.16264233508069592,
          "high": 52511.21,
          "low": 52148.87
        },
        {
          "symbol": "^IXIC",
          "label": "Nasdaq",
          "price": 25814.3,
          "change_pct": -0.08867418993258248,
          "high": 25820.238,
          "low": 25681.324
        },
        {
          "symbol": "^BVSP",
          "label": "Ibovespa",
          "price": 175510.56,
          "change_pct": 1.2603764005400215,
          "high": 176807.27,
          "low": 173328.05
        },
        {
          "symbol": "IFIX.SA",
          "label": "IFIX",
          "price": 3815.05,
          "change_pct": -0.3310064477025388,
          "high": 3828.45,
          "low": 3814.72
        },
        {
          "symbol": "^VIX",
          "label": "VIX",
          "price": 16.98,
          "change_pct": -0.4105527284036081,
          "high": 17.75,
          "low": 16.76
        }
      ]
    },
    {
      "name": "Energia",
      "items": [
        {
          "symbol": "CL=F",
          "label": "WTI | Petróleo",
          "price": 87.09,
          "change_pct": 2.5674199079836337,
          "high": 88.61,
          "low": 84.44
        },
        {
          "symbol": "BZ=F",
          "label": "Brent | Petróleo",
          "price": 94.26,
          "change_pct": 3.5710337188045553,
          "high": 85.14,
          "low": 84.01
        },
        {
          "symbol": "NG=F",
          "label": "Nat Gas | Gás Natural",
          "price": 2.913,
          "change_pct": 1.6753923317095563,
          "high": 2.94,
          "low": 2.865
        }
      ]
    },
    {
      "name": "Metais",
      "items": [
        {
          "symbol": "GC=F",
          "label": "Gold | Ouro",
          "price": 4159.2,
          "change_pct": 2.164031839808344,
          "high": 4168.8,
          "low": 4081.0
        },
        {
          "symbol": "SI=F",
          "label": "Silver | Prata",
          "price": 60.63,
          "change_pct": 3.050906677078663,
          "high": 61.27,
          "low": 59.025
        },
        {
          "symbol": "PL=F",
          "label": "Platinum | Platina",
          "price": 1655.9,
          "change_pct": 1.8326071497125913,
          "high": 1680.7,
          "low": 1636.1
        },
        {
          "symbol": "HG=F",
          "label": "Copper | Cobre",
          "price": 6.5055,
          "change_pct": -0.08447483136948936,
          "high": 6.563,
          "low": 6.491
        }
      ]
    },
    {
      "name": "Graos",
      "items": [
        {
          "symbol": "ZC=F",
          "label": "Corn | Milho",
          "price": 484.0,
          "change_pct": 6.902263942573164,
          "high": 486.5,
          "low": 474.75
        },
        {
          "symbol": "ZW=F",
          "label": "Wheat | Trigo",
          "price": 703.0,
          "change_pct": 3.687315634218289,
          "high": 706.5,
          "low": 678.0
        },
        {
          "symbol": "ZS=F",
          "label": "Soybean | Soja",
          "price": 1235.0,
          "change_pct": 1.2710127101271012,
          "high": 1239.0,
          "low": 1217.75
        }
      ]
    },
    {
      "name": "Softs",
      "items": [
        {
          "symbol": "KC=F",
          "label": "Coffee | Café",
          "price": 314.7,
          "change_pct": -5.196569234126956,
          "high": 324.6,
          "low": 314.15
        },
        {
          "symbol": "OJ=F",
          "label": "Orange Juice | Suco de Laranja",
          "price": 148.1,
          "change_pct": 2.9902620702271387,
          "high": 149.4,
          "low": 140.55
        },
        {
          "symbol": "CT=F",
          "label": "Cotton | Algodão",
          "price": 80.43,
          "change_pct": 1.861703308728158,
          "high": 81.75,
          "low": 79.75
        },
        {
          "symbol": "SB=F",
          "label": "Sugar | Açúcar",
          "price": 14.69,
          "change_pct": -1.276882479701898,
          "high": 14.94,
          "low": 14.67
        }
      ]
    },
    {
      "name": "Moedas",
      "items": [
        {
          "symbol": "DX-Y.NYB",
          "label": "DXY",
          "price": 101.105,
          "change_pct": -0.07412562260285019,
          "high": 101.198,
          "low": 101.02
        },
        {
          "symbol": "BRL=X",
          "label": "USD/BRL",
          "price": 5.0625,
          "change_pct": -0.8208635027053062,
          "high": 5.0837,
          "low": 5.0484
        },
        {
          "symbol": "EURUSD=X",
          "label": "EUR/USD",
          "price": 1.1412,
          "change_pct": -0.05370046615118552,
          "high": 1.1423,
          "low": 1.1401
        },
        {
          "symbol": "GBP=X",
          "label": "USD/GBP",
          "price": 0.7477,
          "change_pct": 0.4284704084324471,
          "high": 0.7486,
          "low": 0.7466
        },
        {
          "symbol": "JPY=X",
          "label": "USD/JPY",
          "price": 163.112,
          "change_pct": 0.38464645796857677,
          "high": 163.228,
          "low": 162.662
        },
        {
          "symbol": "BTC-USD",
          "label": "Bitcoin | BTC/USD",
          "price": 65973.88,
          "change_pct": -0.7988030997611016,
          "high": 66684.68,
          "low": 65540.15
        },
        {
          "symbol": "ETH-USD",
          "label": "Ethereum | ETH/USD",
          "price": 1947.56,
          "change_pct": 0.9944188001509088,
          "high": 1943.3142,
          "low": 1909.6101
        }
      ]
    }
  ]
}