{
  "generated_at": "2026-07-17T21:57:22Z",
  "categories": [
    {
      "name": "Indices",
      "items": [
        {
          "symbol": "^GSPC",
          "label": "S&P 500",
          "error": "HTTP Error 429: Too Many Requests"
        },
        {
          "symbol": "^DJI",
          "label": "Dow Jones",
          "error": "HTTP Error 429: Too Many Requests"
        },
        {
          "symbol": "^IXIC",
          "label": "Nasdaq",
          "error": "HTTP Error 429: Too Many Requests"
        },
        {
          "symbol": "^BVSP",
          "label": "Ibovespa",
          "error": "HTTP Error 429: Too Many Requests"
        },
        {
          "symbol": "IFIX.SA",
          "label": "IFIX",
          "error": "HTTP Error 429: Too Many Requests"
        },
        {
          "symbol": "^VIX",
          "label": "VIX",
          "error": "HTTP Error 429: Too Many Requests"
        }
      ]
    },
    {
      "name": "Energia",
      "items": [
        {
          "symbol": "CL=F",
          "label": "WTI | Petróleo",
          "error": "HTTP Error 429: Too Many Requests"
        },
        {
          "symbol": "BZ=F",
          "label": "Brent | Petróleo",
          "error": "HTTP Error 429: Too Many Requests"
        },
        {
          "symbol": "NG=F",
          "label": "Nat Gas | Gás Natural",
          "error": "HTTP Error 429: Too Many Requests"
        }
      ]
    },
    {
      "name": "Metais",
      "items": [
        {
          "symbol": "GC=F",
          "label": "Gold | Ouro",
          "error": "HTTP Error 429: Too Many Requests"
        },
        {
          "symbol": "SI=F",
          "label": "Silver | Prata",
          "error": "HTTP Error 429: Too Many Requests"
        },
        {
          "symbol": "PL=F",
          "label": "Platinum | Platina",
          "error": "HTTP Error 429: Too Many Requests"
        },
        {
          "symbol": "HG=F",
          "label": "Copper | Cobre",
          "error": "HTTP Error 429: Too Many Requests"
        }
      ]
    },
    {
      "name": "Graos",
      "items": [
        {
          "symbol": "ZC=F",
          "label": "Corn | Milho",
          "error": "HTTP Error 429: Too Many Requests"
        },
        {
          "symbol": "ZW=F",
          "label": "Wheat | Trigo",
          "error": "HTTP Error 429: Too Many Requests"
        },
        {
          "symbol": "ZS=F",
          "label": "Soybean | Soja",
          "error": "HTTP Error 429: Too Many Requests"
        }
      ]
    },
    {
      "name": "Softs",
      "items": [
        {
          "symbol": "KC=F",
          "label": "Coffee | Café",
          "error": "HTTP Error 429: Too Many Requests"
        },
        {
          "symbol": "OJ=F",
          "label": "Orange Juice | Suco de Laranja",
          "error": "HTTP Error 429: Too Many Requests"
        },
        {
          "symbol": "CT=F",
          "label": "Cotton | Algodão",
          "error": "HTTP Error 429: Too Many Requests"
        },
        {
          "symbol": "SB=F",
          "label": "Sugar | Açúcar",
          "error": "HTTP Error 429: Too Many Requests"
        }
      ]
    },
    {
      "name": "Moedas",
      "items": [
        {
          "symbol": "DX-Y.NYB",
          "label": "DXY",
          "error": "HTTP Error 429: Too Many Requests"
        },
        {
          "symbol": "BRL=X",
          "label": "USD/BRL",
          "error": "HTTP Error 429: Too Many Requests"
        },
        {
          "symbol": "EURUSD=X",
          "label": "EUR/USD",
          "error": "HTTP Error 429: Too Many Requests"
        },
        {
          "symbol": "GBP=X",
          "label": "USD/GBP",
          "error": "HTTP Error 429: Too Many Requests"
        },
        {
          "symbol": "JPY=X",
          "label": "USD/JPY",
          "error": "HTTP Error 429: Too Many Requests"
        },
        {
          "symbol": "BTC-USD",
          "label": "Bitcoin | BTC/USD",
          "error": "HTTP Error 429: Too Many Requests"
        },
        {
          "symbol": "ETH-USD",
          "label": "Ethereum | ETH/USD",
          "error": "HTTP Error 429: Too Many Requests"
        }
      ]
    }
  ]
}