{
  "generated_at": "2026-07-21T14:25:25Z",
  "categories": [
    {
      "name": "Indices",
      "items": [
        {
          "symbol": "^GSPC",
          "label": "S&P 500",
          "price": 7485.44,
          "change_pct": 0.5664198587271642,
          "high": 7492.5,
          "low": 7467.86
        },
        {
          "symbol": "^DJI",
          "label": "Dow Jones",
          "price": 52161.07,
          "change_pct": 0.6207809883480715,
          "high": 52175.15,
          "low": 51890.1
        },
        {
          "symbol": "^IXIC",
          "label": "Nasdaq",
          "price": 25736.379,
          "change_pct": 0.8950449199135232,
          "high": 25772.549,
          "low": 25672.828
        },
        {
          "symbol": "^BVSP",
          "label": "Ibovespa",
          "price": 173097.44,
          "change_pct": -0.15778878820563857,
          "high": 173719.5,
          "low": 172674.83
        },
        {
          "symbol": "IFIX.SA",
          "label": "IFIX",
          "price": 3837.78,
          "change_pct": 0.0033874897398175744,
          "high": 3841.73,
          "low": 3835.48
        },
        {
          "symbol": "^VIX",
          "label": "VIX",
          "price": 17.74,
          "change_pct": -4.879354622753543,
          "high": 17.99,
          "low": 17.42
        }
      ]
    },
    {
      "name": "Energia",
      "items": [
        {
          "symbol": "CL=F",
          "label": "WTI | Petróleo",
          "price": 84.54,
          "change_pct": 1.5739476033041413,
          "high": 84.95,
          "low": 81.39
        },
        {
          "symbol": "BZ=F",
          "label": "Brent | Petróleo",
          "price": 91.46,
          "change_pct": 2.5106464342628665,
          "high": 91.59,
          "low": 87.88
        },
        {
          "symbol": "NG=F",
          "label": "Nat Gas | Gás Natural",
          "price": 2.866,
          "change_pct": 0.20979388546354727,
          "high": 2.892,
          "low": 2.839
        }
      ]
    },
    {
      "name": "Metais",
      "items": [
        {
          "symbol": "GC=F",
          "label": "Gold | Ouro",
          "price": 4068.0,
          "change_pct": 1.4387938675245975,
          "high": 4088.4,
          "low": 4003.3
        },
        {
          "symbol": "SI=F",
          "label": "Silver | Prata",
          "price": 59.125,
          "change_pct": 4.0896481421499615,
          "high": 59.55,
          "low": 56.38
        },
        {
          "symbol": "PL=F",
          "label": "Platinum | Platina",
          "price": 1630.6,
          "change_pct": 2.4117604575896445,
          "high": 1647.4,
          "low": 1594.3
        },
        {
          "symbol": "HG=F",
          "label": "Copper | Cobre",
          "price": 6.518,
          "change_pct": 3.4767458493439762,
          "high": 6.545,
          "low": 6.328
        }
      ]
    },
    {
      "name": "Graos",
      "items": [
        {
          "symbol": "ZC=F",
          "label": "Corn | Milho",
          "price": 472.25,
          "change_pct": 5.061179087875417,
          "high": 474.25,
          "low": 469.0
        },
        {
          "symbol": "ZW=F",
          "label": "Wheat | Trigo",
          "price": 670.0,
          "change_pct": -0.5934718100890208,
          "high": 678.75,
          "low": 665.25
        },
        {
          "symbol": "ZS=F",
          "label": "Soybean | Soja",
          "price": 1220.5,
          "change_pct": -0.4486133768352365,
          "high": 1230.25,
          "low": 1220.25
        }
      ]
    },
    {
      "name": "Softs",
      "items": [
        {
          "symbol": "KC=F",
          "label": "Coffee | Café",
          "price": 325.55,
          "change_pct": -2.6465293235692866,
          "high": 335.4,
          "low": 321.35
        },
        {
          "symbol": "OJ=F",
          "label": "Orange Juice | Suco de Laranja",
          "price": 146.3,
          "change_pct": -0.7462645468336071,
          "high": 149.65,
          "low": 143.65
        },
        {
          "symbol": "CT=F",
          "label": "Cotton | Algodão",
          "price": 79.51,
          "change_pct": 2.7659262988878623,
          "high": 81.75,
          "low": 79.75
        },
        {
          "symbol": "SB=F",
          "label": "Sugar | Açúcar",
          "price": 14.78,
          "change_pct": -0.2699034794055293,
          "high": 14.92,
          "low": 14.76
        }
      ]
    },
    {
      "name": "Moedas",
      "items": [
        {
          "symbol": "DX-Y.NYB",
          "label": "DXY",
          "price": 101.029,
          "change_pct": 0.03861980102532238,
          "high": 101.13,
          "low": 100.863
        },
        {
          "symbol": "BRL=X",
          "label": "USD/BRL",
          "price": 5.0757,
          "change_pct": -1.0005823384422214,
          "high": 5.0924,
          "low": 5.0683
        },
        {
          "symbol": "EURUSD=X",
          "label": "EUR/USD",
          "price": 1.1416,
          "change_pct": -0.10201219376075304,
          "high": 1.1431,
          "low": 1.1409
        },
        {
          "symbol": "GBP=X",
          "label": "USD/GBP",
          "price": 0.7468,
          "change_pct": 0.41683103666715654,
          "high": 0.7484,
          "low": 0.7431
        },
        {
          "symbol": "JPY=X",
          "label": "USD/JPY",
          "price": 162.903,
          "change_pct": 0.2406016833568234,
          "high": 162.928,
          "low": 162.41
        },
        {
          "symbol": "BTC-USD",
          "label": "Bitcoin | BTC/USD",
          "price": 66634.13,
          "change_pct": 2.152540345952405,
          "high": 66890.5,
          "low": 65138.832
        },
        {
          "symbol": "ETH-USD",
          "label": "Ethereum | ETH/USD",
          "price": 1930.2,
          "change_pct": 1.3888885148516017,
          "high": 1945.1078,
          "low": 1901.2704
        }
      ]
    }
  ]
}